scipp-25.12.0.dist-info/RECORD
scipp-25.12.0.dist-info/WHEEL
scipp-25.12.0.dist-info/METADATA
scipp-25.12.0.dist-info/licenses/LICENSE
scipp/logging.py
scipp/_scipp.pyi
scipp/reduction.py
scipp/plotting.py
scipp/__init__.py
scipp/operations.py
scipp/curve_fit.py
scipp/object_list.py
scipp/py.typed
scipp/_extend_units.py
scipp/_binding.py
scipp/typing.py
scipp/serialization.py
scipp/_scipp.so
scipp/visualization/show.py
scipp/visualization/html.py
scipp/visualization/__init__.py
scipp/visualization/formatting_datagroup_html.py
scipp/visualization/formatting_html.py
scipp/visualization/resources.py
scipp/visualization/table.py
scipp/visualization/colors.py
scipp/visualization/templates/datagroup.css
scipp/visualization/templates/dg_repr.html
scipp/visualization/templates/__init__.py
scipp/visualization/templates/icons-svg-inline.html
scipp/visualization/templates/dg_detail_list.html
scipp/visualization/templates/style.css
scipp/visualization/templates/dg_collapsible_row.html
scipp/visualization/templates/dg_atomic_row.html
scipp/compat/xarray_compat.py
scipp/compat/__init__.py
scipp/compat/pandas_compat.py
scipp/compat/dict.py
scipp/compat/wrapping.py
scipp/core/binning.py
scipp/core/arithmetic.py
scipp/core/_sizes.py
scipp/core/bin_remapping.py
scipp/core/logical.py
scipp/core/reduction.py
scipp/core/dimensions.py
scipp/core/util.py
scipp/core/cpp_classes.py
scipp/core/domains.py
scipp/core/like.py
scipp/core/argument_handlers.py
scipp/core/__init__.py
scipp/core/_cpp_wrapper_util.py
scipp/core/assignments.py
scipp/core/comparison.py
scipp/core/variable.py
scipp/core/dataset.py
scipp/core/operations.py
scipp/core/cumulative.py
scipp/core/cpp_classes.pyi
scipp/core/hyperbolic.py
scipp/core/structured.py
scipp/core/data_group.py
scipp/core/shape.py
scipp/core/unary.py
scipp/core/math.py
scipp/core/trigonometry.py
scipp/core/groupby.py
scipp/core/concepts.py
scipp/core/bins.py
scipp/core/counts.py
scipp/sphinxext/autoplot.py
scipp/sphinxext/__init__.py
scipp/binning/__init__.py
scipp/include/units/units_decl.hpp
