Metadata-Version: 2.4
Name: scipp
Version: 25.12.0
Summary: Multi-dimensional data arrays with labeled dimensions
Author: Scipp contributors (https://github.com/scipp)
License-Expression: BSD-3-Clause
License-File: LICENSE
Classifier: Intended Audience :: Science/Research
Classifier: Natural Language :: English
Classifier: Programming Language :: Python :: 3
Classifier: Programming Language :: Python :: 3 :: Only
Classifier: Programming Language :: Python :: 3.11
Classifier: Programming Language :: Python :: 3.12
Classifier: Programming Language :: Python :: 3.13
Classifier: Programming Language :: Python :: 3.14
Classifier: Operating System :: MacOS :: MacOS X
Classifier: Operating System :: Microsoft :: Windows
Classifier: Operating System :: POSIX :: Linux
Classifier: Topic :: Scientific/Engineering
Classifier: Typing :: Typed
Project-URL: Documentation, https://scipp.github.io/
Project-URL: Source, https://github.com/scipp/scipp
Project-URL: Bug Tracker, https://github.com/scipp/scipp/issues
Requires-Python: >=3.11
Requires-Dist: numpy>=2
Provides-Extra: test
Requires-Dist: pytest; extra == "test"
Requires-Dist: matplotlib; extra == "test"
Requires-Dist: beautifulsoup4; extra == "test"
Requires-Dist: ipython; extra == "test"
Provides-Extra: extra
Requires-Dist: h5py; extra == "extra"
Requires-Dist: scipy>=1.7.0; extra == "extra"
Requires-Dist: graphviz; extra == "extra"
Requires-Dist: pooch; extra == "extra"
Requires-Dist: plopp; extra == "extra"
Requires-Dist: matplotlib; extra == "extra"
Provides-Extra: all
Requires-Dist: scipp[extra]; extra == "all"
Requires-Dist: ipympl; extra == "all"
Requires-Dist: ipython; extra == "all"
Requires-Dist: ipywidgets; extra == "all"
Requires-Dist: jupyterlab; extra == "all"
Requires-Dist: jupyterlab-widgets; extra == "all"
Requires-Dist: jupyter_nbextensions_configurator; extra == "all"
Requires-Dist: nodejs; extra == "all"
Requires-Dist: pythreejs; extra == "all"
